Workbook

Sheet ALG Caseware
A1: WP Index ID | B1: Process Flow | C1: Process Flow-2 | D1: Type | E1: FS Section | F1: Document Name | G1: Source | H1: File Format | I1: PPC Form Reference | J1: Notes | L1: Time Bucket | M1: Rationale | N1: Audit Manager Override | O1: Audit Reviewer Note
A2: FS-FINAL | D2: FS Section | E2: Financial Statements and Deliverables Section | F2: Final PDF Copy of the Audited Financial Statements | G2: =_xlfn.XLOOKUP(F2,'NPO Caseware'!G:G,'NPO Caseware'!H:H) -> HCLLP WP | H2: =_xlfn.XLOOKUP(F2,'NPO Caseware'!G:G,'NPO Caseware'!I:I) -> PDF | L2: time_static | M2: FS draft/final — FS layout stable
A3: FS-CV | D3: FS Section | E3: Financial Statements and Deliverables Section | F3: Working Copy of the CaseView Financial Statements | G3: =_xlfn.XLOOKUP(F3,'NPO Caseware'!G:G,'NPO Caseware'!H:H) -> HCLLP WP | H3: =_xlfn.XLOOKUP(F3,'NPO Caseware'!G:G,'NPO Caseware'!I:I) -> PDF | L3: time_static | M3: CaseView FS working copy — layout stable
A4: FS-CV-1 | D4: FS Section | E4: Financial Statements and Deliverables Section | F4: Cash Flow Worksheet (if applicable) | G4: =_xlfn.XLOOKUP(F4,'NPO Caseware'!G:G,'NPO Caseware'!H:H) -> HCLLP WP | H4: =_xlfn.XLOOKUP(F4,'NPO Caseware'!G:G,'NPO Caseware'!I:I) -> Excel | L4: time_static | M4: cash flow worksheet — format stable
A5: FS-PROG | D5: FS Section | E5: Financial Statements and Deliverables Section | F5: Audit Program for General Auditing and Completion Procedures | G5: =_xlfn.XLOOKUP(F5,'NPO Caseware'!G:G,'NPO Caseware'!H:H) -> PPC | H5: =_xlfn.XLOOKUP(F5,'NPO Caseware'!G:G,'NPO Caseware'!I:I) -> Word | I5: ALG-AP-20 | L5: time_static | M5: audit program — standard procedure
A6: FS-PROG-1 | D6: FS Section | E6: Financial Statements and Deliverables Section | F6: Additional General Auditing and Completion Procedures for an Initial Audit (If applicable) | G6: PPC | H6: Word | I6: ALG-IA-20 | J6: Use only if this is a first year audit for Harshwal & CO/Blue Arrow CPAs | L6: time_static | M6: FS deliverables — default standard procedure (section default)
A7: FS-1 | D7: FS Section | E7: Financial Statements and Deliverables Section | F7: Governmental Disclosure Checklist | G7: PPC | H7: Word | I7: ALG-CX-13.1 | L7: time_static | M7: disclosure checklist — slowly evolving
A8: FS-2 | D8: FS Section | E8: Financial Statements and Deliverables Section | F8: Management Representation Letter (Client Endorsed) | G8: =_xlfn.XLOOKUP(F8,'NPO Caseware'!G:G,'NPO Caseware'!H:H) -> PBC | H8: =_xlfn.XLOOKUP(F8,'NPO Caseware'!G:G,'NPO Caseware'!I:I) -> PDF | L8: time_static | M8: MRL template — standard
A9: FS-2-1 | D9: FS Section | E9: Financial Statements and Deliverables Section | F9: Management Representation Letter Template | G9: =_xlfn.XLOOKUP(F9,'NPO Caseware'!G:G,'NPO Caseware'!H:H) -> PPC | H9: =_xlfn.XLOOKUP(F9,'NPO Caseware'!G:G,'NPO Caseware'!I:I) -> Word | I9: ALG-CL-3.1 | L9: time_static | M9: MRL template — standard
A10: FS-3 | D10: FS Section | E10: Financial Statements and Deliverables Section | F10: Legal Representation Letter (Returned Response from Attorney) | G10: =_xlfn.XLOOKUP(F10,'NPO Caseware'!G:G,'NPO Caseware'!H:H) -> HCLLP WP | H10: =_xlfn.XLOOKUP(F10,'NPO Caseware'!G:G,'NPO Caseware'!I:I) -> PDF | L10: time_static | M10: FS deliverables — default standard procedure (section default)
A11: FS-4 | D11: FS Section | E11: Financial Statements and Deliverables Section | F11: Communication to Those Charged with Governance at Conclusion (Final PDF Copy provided to Client) | G11: =_xlfn.XLOOKUP(F11,'NPO Caseware'!G:G,'NPO Caseware'!H:H) -> HCLLP WP | H11: =_xlfn.XLOOKUP(F11,'NPO Caseware'!G:G,'NPO Caseware'!I:I) -> PDF | L11: time_static | M11: FS draft/final — FS layout stable
A12: FS-4-1 | D12: FS Section | E12: Financial Statements and Deliverables Section | F12: Communication to Those Charged with Governance at Conclusion Template | G12: =_xlfn.XLOOKUP(F12,'NPO Caseware'!G:G,'NPO Caseware'!H:H) -> PPC | H12: =_xlfn.XLOOKUP(F12,'NPO Caseware'!G:G,'NPO Caseware'!I:I) -> Word | I12: ALG-CL-5.2 | L12: time_static | M12: TCWG comm — standard
A13: FS-5 | D13: FS Section | E13: Financial Statements and Deliverables Section | F13: Audit Presentation PowerPoint | G13: =_xlfn.XLOOKUP(F13,'NPO Caseware'!G:G,'NPO Caseware'!H:H) -> HCLLP WP | H13: =_xlfn.XLOOKUP(F13,'NPO Caseware'!G:G,'NPO Caseware'!I:I) -> PPT | L13: time_static | M13: FS deliverables — default standard procedure (section default)
A14: FS-6 | D14: FS Section | E14: Financial Statements and Deliverables Section | F14: Final Analytical Procedures - Opinion Unit #1 | G14: HCLLP WP | H14: Excel | L14: time_static | M14: substantive procedure — standard
A15: FS-6-1 | D15: FS Section | E15: Financial Statements and Deliverables Section | F15: Final Analytical Procedures - Opinion Unit #2 | G15: HCLLP WP | H15: Excel | L15: time_static | M15: substantive procedure — standard
A16: FS-6-2 | D16: FS Section | E16: Financial Statements and Deliverables Section | F16: Final Analytical Procedures - Opinion Unit #3 | G16: HCLLP WP | H16: Excel | L16: time_static | M16: substantive procedure — standard
A17: FS-6-3 | D17: FS Section | E17: Financial Statements and Deliverables Section | F17: Final Analytical Procedures - Opinion Unit #4 | G17: HCLLP WP | H17: Excel | L17: time_static | M17: substantive procedure — standard
A18: FS-7 | D18: FS Section | E18: Financial Statements and Deliverables Section | F18: Estimates Identification and Retrospective Review | G18: =_xlfn.XLOOKUP(F18,'NPO Caseware'!G:G,'NPO Caseware'!H:H) -> PPC | H18: =_xlfn.XLOOKUP(F18,'NPO Caseware'!G:G,'NPO Caseware'!I:I) -> Word | I18: ALG-CX-3.6 | L18: time_static | M18: FS deliverables — default standard procedure (section default)
A19: FS-8 | D19: FS Section | E19: Financial Statements and Deliverables Section | F19: Supervision, Review and Approval Form | G19: =_xlfn.XLOOKUP(F19,'NPO Caseware'!G:G,'NPO Caseware'!H:H) -> PPC | H19: =_xlfn.XLOOKUP(F19,'NPO Caseware'!G:G,'NPO Caseware'!I:I) -> Word | I19: ALG-CX-14 | L19: time_static | M19: supervision/review form — standard
A20: FS-9 | D20: FS Section | E20: Financial Statements and Deliverables Section | F20: Retirment Plan Employee and Employer Contribution Report - Footnote Support | G20: =_xlfn.XLOOKUP(F20,'NPO Caseware'!G:G,'NPO Caseware'!H:H) -> PBC | H20: =_xlfn.XLOOKUP(F20,'NPO Caseware'!G:G,'NPO Caseware'!I:I) -> PDF | L20: time_static | M20: FS deliverables — default standard procedure (section default)
A21: FS-9-1 | D21: FS Section | E21: Financial Statements and Deliverables Section | F21: Additional FS Footnote Support #2 | G21: =_xlfn.XLOOKUP(F21,'NPO Caseware'!G:G,'NPO Caseware'!H:H) -> PBC | H21: =_xlfn.XLOOKUP(F21,'NPO Caseware'!G:G,'NPO Caseware'!I:I) -> PDF | L21: time_static | M21: FS deliverables — default standard procedure (section default)
A22: FS-9-2 | D22: FS Section | E22: Financial Statements and Deliverables Section | F22: Additional FS Footnote Support #3 | G22: =_xlfn.XLOOKUP(F22,'NPO Caseware'!G:G,'NPO Caseware'!H:H) -> PBC | H22: =_xlfn.XLOOKUP(F22,'NPO Caseware'!G:G,'NPO Caseware'!I:I) -> PDF | L22: time_static | M22: FS deliverables — default standard procedure (section default)
A23: FS-10 | D23: FS Section | E23: Financial Statements and Deliverables Section | F23: Component Audited FS (if applicable) | G23: PBC | H23: PDF | L23: time_static | M23: group audit — standard procedure
A24: FS-10-1 | D24: FS Section | E24: Financial Statements and Deliverables Section | F24: Request for Representation from Component Auditor When Reference Will be Made (if applicable) | G24: PPC | H24: Word | I24: ALG-CX-14.1 | L24: time_static | M24: group audit — standard procedure
A25: FS-10-2 | D25: FS Section | E25: Financial Statements and Deliverables Section | F25: Letter of Instructions from Group Auditor to Component Auditors When Reference Will be Made (if applicable) | G25: PPC | H25: Word | I25: ALG-CX-14.3 | L25: time_static | M25: group audit — standard procedure
A26: FS-10-3 | D26: FS Section | E26: Financial Statements and Deliverables Section | F26: Peer Review Report of Component Auditor (if applicable) | G26: PBC | H26: PDF | L26: time_static | M26: group audit — standard procedure
A27: ML-1 | D27: ML Section | E27: Management Advisory Letter and Findings Section | F27: Schedule of Findings and Questioned Costs | G27: =_xlfn.XLOOKUP(F27,'NPO Caseware'!G:G,'NPO Caseware'!H:H) -> HCLLP WP | H27: =_xlfn.XLOOKUP(F27,'NPO Caseware'!G:G,'NPO Caseware'!I:I) -> Caseview | L27: time_static | M27: questioned costs listing — format stable
A28: ML-2 | D28: ML Section | E28: Management Advisory Letter and Findings Section | F28: Corrective Action Plan (Provided by Client) | G28: =_xlfn.XLOOKUP(F28,'NPO Caseware'!G:G,'NPO Caseware'!H:H) -> PBC | H28: =_xlfn.XLOOKUP(F28,'NPO Caseware'!G:G,'NPO Caseware'!I:I) -> Word | L28: time_static | M28: ML/findings — finding structure procedural (section default)
A29: ML-3 | D29: ML Section | E29: Management Advisory Letter and Findings Section | F29: Inventory Tracking Listing of Findings and Questioned Costs - Financial Statement Findings | G29: =_xlfn.XLOOKUP(F29,'NPO Caseware'!G:G,'NPO Caseware'!H:H) -> HCLLP WP | H29: =_xlfn.XLOOKUP(F29,'NPO Caseware'!G:G,'NPO Caseware'!I:I) -> Caseview | L29: time_static | M29: questioned costs listing — format stable
A30: ML-3-1 | D30: ML Section | E30: Management Advisory Letter and Findings Section | F30: Inventory Tracking Listing of Findings and Questioned Costs - Federal Award Findings | G30: =_xlfn.XLOOKUP(F30,'NPO Caseware'!G:G,'NPO Caseware'!H:H) -> HCLLP WP | H30: =_xlfn.XLOOKUP(F30,'NPO Caseware'!G:G,'NPO Caseware'!I:I) -> Caseview | L30: time_static | M30: questioned costs listing — format stable
A31: ML-4 | D31: ML Section | E31: Management Advisory Letter and Findings Section | F31: Control Deficiency Evaluation Worksheet | G31: =_xlfn.XLOOKUP(F31,'NPO Caseware'!G:G,'NPO Caseware'!H:H) -> PPC | H31: =_xlfn.XLOOKUP(F31,'NPO Caseware'!G:G,'NPO Caseware'!I:I) -> Word | I31: ALG-CX-15.1 | L31: time_static | M31: IC evaluation matrix — standard
A32: ML-5 | D32: ML Section | E32: Management Advisory Letter and Findings Section | F32: Noncompliance Evaluation Form - Federal Award Programs | G32: =_xlfn.XLOOKUP(F32,'NPO Caseware'!G:G,'NPO Caseware'!H:H) -> PPC | H32: =_xlfn.XLOOKUP(F32,'NPO Caseware'!G:G,'NPO Caseware'!I:I) -> Word | L32: time_static | M32: ML/findings — finding structure procedural (section default)
A33: ML-6 | D33: ML Section | E33: Management Advisory Letter and Findings Section | F33: Status of Prior Year Findings and Questioned Costs | G33: =_xlfn.XLOOKUP(F33,'NPO Caseware'!G:G,'NPO Caseware'!H:H) -> HCLLP WP | H33: =_xlfn.XLOOKUP(F33,'NPO Caseware'!G:G,'NPO Caseware'!I:I) -> Word | L33: time_static | M33: questioned costs listing — format stable
A34: TB-1 | D34: TB Section | E34: Trial Balance Section | F34: Trial Balance - Opinion Unit #1 [e.g. Governmental Activities] (Automatic CaseWare Document) | G34: HCLLP WP | H34: LeadSheet | L34: time_static | M34: TB — mapping stable 4-5 yrs
A35: TB-1-1 | D35: TB Section | E35: Trial Balance Section | F35: Trial Balance - Opinion Unit #2 (Automatic CaseWare Document) | G35: HCLLP WP | H35: LeadSheet | L35: time_static | M35: TB — mapping stable 4-5 yrs
A36: TB-1-2 | D36: TB Section | E36: Trial Balance Section | F36: Trial Balance - Opinion Unit #3 (Automatic CaseWare Document) | G36: HCLLP WP | H36: LeadSheet | L36: time_static | M36: TB — mapping stable 4-5 yrs
A37: TB-1-3 | D37: TB Section | E37: Trial Balance Section | F37: Trial Balance - Opinion Unit #4 (Automatic CaseWare Document) | G37: HCLLP WP | H37: LeadSheet | L37: time_static | M37: TB — mapping stable 4-5 yrs
A38: TB-2 | D38: TB Section | E38: Trial Balance Section | F38: Trial Balance Import File | G38: HCLLP WP | H38: Excel | L38: time_static | M38: TB — mapping stable 4-5 yrs
A39: TB-3 | D39: TB Section | E39: Trial Balance Section | F39: Adjusting Journal Entries Report (Automatic CaseWare Document) | G39: =_xlfn.XLOOKUP(F39,'NPO Caseware'!G:G,'NPO Caseware'!H:H) -> HCLLP WP | H39: =_xlfn.XLOOKUP(F39,'NPO Caseware'!G:G,'NPO Caseware'!I:I) -> LeadSheet | L39: time_static | M39: AJE/RJE — JE listing format stable
A40: TB-4 | D40: TB Section | E40: Trial Balance Section | F40: Reclassifying Journal Entries Report (Automatic CaseWare Document) | G40: =_xlfn.XLOOKUP(F40,'NPO Caseware'!G:G,'NPO Caseware'!H:H) -> HCLLP WP | H40: =_xlfn.XLOOKUP(F40,'NPO Caseware'!G:G,'NPO Caseware'!I:I) -> LeadSheet | L40: time_static | M40: TB section — format/mapping stable 4-5 yrs (section default)
A41: TB-5 | D41: TB Section | E41: Trial Balance Section | F41: Passed Adjusting Journal Entries Report (Automatic CaseWare Document) | G41: =_xlfn.XLOOKUP(F41,'NPO Caseware'!G:G,'NPO Caseware'!H:H) -> HCLLP WP | H41: =_xlfn.XLOOKUP(F41,'NPO Caseware'!G:G,'NPO Caseware'!I:I) -> LeadSheet | L41: time_static | M41: AJE/RJE — JE listing format stable
A42: TB-6 | D42: TB Section | E42: Trial Balance Section | F42: Audit Difference Evaluation Form - Opinion Unit #1 | G42: PPC | H42: Word | I42: ALG-CX-12.2 | L42: time_static | M42: audit difference eval — format stable
A43: TB-6-1 | D43: TB Section | E43: Trial Balance Section | F43: Audit Difference Evaluation Form - Opinion Unit #2 | G43: PPC | H43: Word | I43: ALG-CX-12.2 | L43: time_static | M43: audit difference eval — format stable
A44: TB-6-2 | D44: TB Section | E44: Trial Balance Section | F44: Audit Difference Evaluation Form - Opinion Unit #3 | G44: PPC | H44: Word | I44: ALG-CX-12.2 | L44: time_static | M44: audit difference eval — format stable
A45: TB-6-3 | D45: TB Section | E45: Trial Balance Section | F45: Audit Difference Evaluation Form - Opinion Unit #4 | G45: PPC | H45: Word | I45: ALG-CX-12.2 | L45: time_static | M45: audit difference eval — format stable
A46: PL-PROG | D46: PL Section | E46: Planning Section | F46: Audit Program for General Planning Procedures | G46: =_xlfn.XLOOKUP(F46,'NPO Caseware'!G:G,'NPO Caseware'!H:H) -> PPC | H46: =_xlfn.XLOOKUP(F46,'NPO Caseware'!G:G,'NPO Caseware'!I:I) -> Word | I46: ALG-AP-10 | L46: time_static | M46: audit program — standard procedure
A47: PL-1 | D47: PL Section | E47: Planning Section | F47: Engagement Acceptance and Continuation Form | G47: =_xlfn.XLOOKUP(F47,'NPO Caseware'!G:G,'NPO Caseware'!H:H) -> PPC | H47: =_xlfn.XLOOKUP(F47,'NPO Caseware'!G:G,'NPO Caseware'!I:I) -> Word | I47: ALG-CX-1.1 | L47: time_static | M47: engagement procedure — standard
A48: PL-2 | D48: PL Section | E48: Planning Section | F48: Evaluating Independence - Yellowbook and GAAS Audits | G48: =_xlfn.XLOOKUP(F48,'NPO Caseware'!G:G,'NPO Caseware'!H:H) -> PPC | H48: =_xlfn.XLOOKUP(F48,'NPO Caseware'!G:G,'NPO Caseware'!I:I) -> Word | I48: ALG-CX-1.3 | L48: time_static | M48: independence checklist — standard procedure
A49: PL-3 | D49: PL Section | E49: Planning Section | F49: Continuing Professional Education Documentation Form | G49: =_xlfn.XLOOKUP(F49,'NPO Caseware'!G:G,'NPO Caseware'!H:H) -> PPC | H49: =_xlfn.XLOOKUP(F49,'NPO Caseware'!G:G,'NPO Caseware'!I:I) -> Word | I49: ALG-CX-1.4 | L49: time_static | M49: Planning — standard procedure by default (section default)
A50: PL-4 | D50: PL Section | E50: Planning Section | F50: Engagement Letter (Client Signed/Endorsed) | G50: HCLLP WP | H50: PDF | L50: time_static | M50: engagement procedure — standard
A51: PL-4-1 | D51: PL Section | E51: Planning Section | F51: Engagement Letter (template sent to client) | G51: HCLLP WP | H51: Caseview | L51: time_static | M51: engagement procedure — standard
A52: PL-5 | D52: PL Section | E52: Planning Section | F52: Communication to Those Charged with Governance During Planning | G52: =_xlfn.XLOOKUP(F52,'NPO Caseware'!G:G,'NPO Caseware'!H:H) -> PPC | H52: =_xlfn.XLOOKUP(F52,'NPO Caseware'!G:G,'NPO Caseware'!I:I) -> Word | I52: ALG-CL-5.1 | L52: time_static | M52: TCWG comm — standard
A53: PL-6 | D53: PL Section | E53: Planning Section | F53: Understanding the Entity and Identifying Risks | G53: =_xlfn.XLOOKUP(F53,'NPO Caseware'!G:G,'NPO Caseware'!H:H) -> PPC | H53: =_xlfn.XLOOKUP(F53,'NPO Caseware'!G:G,'NPO Caseware'!I:I) -> Word | I53: ALG-CX-3.1 | L53: time_static | M53: understanding entity — standard
A54: PL-6-1 | D54: PL Section | E54: Planning Section | F54: Listing of Board Members/Tribal Council including contact information | G54: PBC | H54: PDF | L54: time_static | M54: Planning — standard procedure by default (section default)
A55: PL-6-2 | D55: PL Section | E55: Planning Section | F55: Listing of Management and Key Personnel including contact information | G55: PBC | H55: =_xlfn.XLOOKUP(F55,'NPO Caseware'!G:G,'NPO Caseware'!I:I) -> PDF | L55: time_static | M55: Planning — standard procedure by default (section default)
A56: PL-6-3 | D56: PL Section | E56: Planning Section | F56: Listing of Legal Counsel including contact information | G56: =_xlfn.XLOOKUP(F56,'NPO Caseware'!G:G,'NPO Caseware'!H:H) -> PBC | H56: =_xlfn.XLOOKUP(F56,'NPO Caseware'!G:G,'NPO Caseware'!I:I) -> PDF | L56: time_static | M56: Planning — standard procedure by default (section default)
A57: PL-7 | D57: PL Section | E57: Planning Section | F57: Major Fund Determination Worksheet | G57: HCLLP WP | H57: Caseview | I57: ALG-CX-1.10 | L57: time_sensitive | M57: Major Fund 10% test — GASB threshold parameters
A58: PL-8 | D58: PL Section | E58: Planning Section | F58: Financial Statement Materiality Worksheet for Planning Purposes | G58: =_xlfn.XLOOKUP(F58,'NPO Caseware'!G:G,'NPO Caseware'!H:H) -> HCLLP WP | H58: =_xlfn.XLOOKUP(F58,'NPO Caseware'!G:G,'NPO Caseware'!I:I) -> Caseview | I58: ALG-CX-2.1 | L58: time_sensitive | M58: materiality calc — benchmark %/threshold $ that updates
A59: PL-8-1 | D59: PL Section | E59: Planning Section | F59: Financial Statement Materiality Worksheet - Final Assessment at Conclusion | G59: =_xlfn.XLOOKUP(F59,'NPO Caseware'!G:G,'NPO Caseware'!H:H) -> HCLLP WP | H59: =_xlfn.XLOOKUP(F59,'NPO Caseware'!G:G,'NPO Caseware'!I:I) -> Caseview | I59: ALG-CX-2.1 | L59: time_sensitive | M59: materiality calc — benchmark %/threshold $ that updates
A60: PL-8-2 | D60: PL Section | E60: Planning Section | F60: Analysis of Group Components and Determination of Component Materiality (if applicable) | G60: HCLLP WP | H60: Caseview | I60: ALG-CX-3.5 | L60: time_sensitive | M60: materiality calc — benchmark %/threshold $ that updates
A61: PL-9 | D61: PL Section | E61: Planning Section | F61: Audit Program for Minutes, Contracts, Ordinances, and Laws | G61: =_xlfn.XLOOKUP(F61,'NPO Caseware'!G:G,'NPO Caseware'!H:H) -> PPC | H61: =_xlfn.XLOOKUP(F61,'NPO Caseware'!G:G,'NPO Caseware'!I:I) -> Caseview | I61: ALG-AP-40 | L61: time_static | M61: audit program — standard procedure
A62: PL-9-1 | D62: PL Section | E62: Planning Section | F62: Review of Board Minutes Workpaper | G62: =_xlfn.XLOOKUP(F62,'NPO Caseware'!G:G,'NPO Caseware'!H:H) -> HCLLP WP | H62: =_xlfn.XLOOKUP(F62,'NPO Caseware'!G:G,'NPO Caseware'!I:I) -> Word | L62: time_static | M62: Planning — standard procedure by default (section default)
A63: PL-10 | D63: PL Section | E63: Planning Section | F63: Preliminary Analytical - Opinion Unit #1 (CaseWare Automatic Document) | G63: HCLLP WP | H63: LeadSheet/Excel | L63: time_static | M63: substantive procedure — standard
A64: PL-10-1 | D64: PL Section | E64: Planning Section | F64: Preliminary Analytical - Opinion Unit #2 (CaseWare Automatic Document) | G64: HCLLP WP | H64: LeadSheet/Excel | L64: time_static | M64: substantive procedure — standard
A65: PL-10-2 | D65: PL Section | E65: Planning Section | F65: Preliminary Analytical - Opinion Unit #3 (CaseWare Automatic Document) | G65: HCLLP WP | H65: LeadSheet/Excel | L65: time_static | M65: substantive procedure — standard
A66: PL-10-3 | D66: PL Section | E66: Planning Section | F66: Preliminary Analytical - Opinion Unit #4 (CaseWare Automatic Document) | G66: HCLLP WP | H66: LeadSheet/Excel | L66: time_static | M66: substantive procedure — standard
A67: PL-11 | D67: PL Section | E67: Planning Section | F67: PBC List | G67: =_xlfn.XLOOKUP(F67,'NPO Caseware'!G:G,'NPO Caseware'!H:H) -> HCLLP WP | H67: =_xlfn.XLOOKUP(F67,'NPO Caseware'!G:G,'NPO Caseware'!I:I) -> Excel | L67: time_static | M67: PBC list — standard
A68: PL-12 | D68: PL Section | E68: Planning Section | F68: Confirmation Control Log (Standard Workpaper) | G68: =_xlfn.XLOOKUP(F68,'NPO Caseware'!G:G,'NPO Caseware'!H:H) -> HCLLP WP | H68: =_xlfn.XLOOKUP(F68,'NPO Caseware'!G:G,'NPO Caseware'!I:I) -> Caseview | J68: Remember: AU-C 330.20 requires external confirmations for AR to be sent unless: | L68: time_static | M68: confirmation procedure/template — standard
A69: PL-12-1 | D69: PL Section | E69: Planning Section | F69: Cash Confirmation #1 (Client Endorsed) | G69: =_xlfn.XLOOKUP(F69,'NPO Caseware'!G:G,'NPO Caseware'!H:H) -> HCLLP WP | H69: =_xlfn.XLOOKUP(F69,'NPO Caseware'!G:G,'NPO Caseware'!I:I) -> Caseview | J69: 1) Balance is Immaterial | L69: time_static | M69: confirmation procedure/template — standard
A70: PL-12-1-1 | D70: PL Section | E70: Planning Section | F70: Cash Confirmation #1 Template | G70: =_xlfn.XLOOKUP(F70,'NPO Caseware'!G:G,'NPO Caseware'!H:H) -> HCLLP WP | H70: =_xlfn.XLOOKUP(F70,'NPO Caseware'!G:G,'NPO Caseware'!I:I) -> Caseview | J70: 2) External Confirmations would be ineffective | L70: time_static | M70: confirmation procedure/template — standard
A71: PL-12-2 | D71: PL Section | E71: Planning Section | F71: Cash Confirmation #2 (Client Endorsed) | G71: =_xlfn.XLOOKUP(F71,'NPO Caseware'!G:G,'NPO Caseware'!H:H) -> HCLLP WP | H71: =_xlfn.XLOOKUP(F71,'NPO Caseware'!G:G,'NPO Caseware'!I:I) -> Caseview | J71: 3) The Auditor's risk of material misstatement is low and other planned procedures address | L71: time_static | M71: confirmation procedure/template — standard
A72: PL-12-2-1 | D72: PL Section | E72: Planning Section | F72: Cash Confirmation #2 Template | G72: =_xlfn.XLOOKUP(F72,'NPO Caseware'!G:G,'NPO Caseware'!H:H) -> HCLLP WP | H72: =_xlfn.XLOOKUP(F72,'NPO Caseware'!G:G,'NPO Caseware'!I:I) -> Caseview | J72: the assessed risk. | L72: time_static | M72: confirmation procedure/template — standard
A73: PL-12-3 | D73: PL Section | E73: Planning Section | F73: AR Confirmation #1 (Client Endorsed) | G73: =_xlfn.XLOOKUP(F73,'NPO Caseware'!G:G,'NPO Caseware'!H:H) -> HCLLP WP | H73: =_xlfn.XLOOKUP(F73,'NPO Caseware'!G:G,'NPO Caseware'!I:I) -> Caseview | J73: Document witin PL-12 the reason for not sending AR confirmations if they are not | L73: time_static | M73: confirmation procedure/template — standard
A74: PL-12-3-1 | D74: PL Section | E74: Planning Section | F74: AR Confirmation #1 Template | G74: =_xlfn.XLOOKUP(F74,'NPO Caseware'!G:G,'NPO Caseware'!H:H) -> HCLLP WP | H74: =_xlfn.XLOOKUP(F74,'NPO Caseware'!G:G,'NPO Caseware'!I:I) -> Caseview | J74: sent. | L74: time_static | M74: confirmation procedure/template — standard
A75: PL-12-4 | D75: PL Section | E75: Planning Section | F75: AR Confirmation #2 (Client Endorsed) | G75: =_xlfn.XLOOKUP(F75,'NPO Caseware'!G:G,'NPO Caseware'!H:H) -> HCLLP WP | H75: =_xlfn.XLOOKUP(F75,'NPO Caseware'!G:G,'NPO Caseware'!I:I) -> Caseview | L75: time_static | M75: confirmation procedure/template — standard
A76: PL-12-4-1 | D76: PL Section | E76: Planning Section | F76: AR Confirmation #2 Template | G76: =_xlfn.XLOOKUP(F76,'NPO Caseware'!G:G,'NPO Caseware'!H:H) -> HCLLP WP | H76: =_xlfn.XLOOKUP(F76,'NPO Caseware'!G:G,'NPO Caseware'!I:I) -> Caseview | L76: time_static | M76: confirmation procedure/template — standard
A77: PL-12-5 | D77: PL Section | E77: Planning Section | F77: Investments Confirmation #1 (Client Endorsed) | G77: =_xlfn.XLOOKUP(F77,'NPO Caseware'!G:G,'NPO Caseware'!H:H) -> HCLLP WP | H77: =_xlfn.XLOOKUP(F77,'NPO Caseware'!G:G,'NPO Caseware'!I:I) -> Caseview | L77: time_static | M77: confirmation procedure/template — standard
A78: PL-12-5-1 | D78: PL Section | E78: Planning Section | F78: Investments Confirmation #1 Template | G78: =_xlfn.XLOOKUP(F78,'NPO Caseware'!G:G,'NPO Caseware'!H:H) -> HCLLP WP | H78: =_xlfn.XLOOKUP(F78,'NPO Caseware'!G:G,'NPO Caseware'!I:I) -> Caseview | L78: time_static | M78: confirmation procedure/template — standard
A79: PL-12-6 | D79: PL Section | E79: Planning Section | F79: Debt Confirmation #1 (Client Endorsed) | G79: =_xlfn.XLOOKUP(F79,'NPO Caseware'!G:G,'NPO Caseware'!H:H) -> HCLLP WP | H79: =_xlfn.XLOOKUP(F79,'NPO Caseware'!G:G,'NPO Caseware'!I:I) -> Caseview | L79: time_static | M79: confirmation procedure/template — standard
A80: PL-12-6-1 | D80: PL Section | E80: Planning Section | F80: Debt Confirmation #1 Template | G80: =_xlfn.XLOOKUP(F80,'NPO Caseware'!G:G,'NPO Caseware'!H:H) -> HCLLP WP | H80: =_xlfn.XLOOKUP(F80,'NPO Caseware'!G:G,'NPO Caseware'!I:I) -> Caseview | L80: time_static | M80: confirmation procedure/template — standard
A81: PL-12-7 | D81: PL Section | E81: Planning Section | F81: Debt Confirmation #2 (Client Endorsed) | G81: =_xlfn.XLOOKUP(F81,'NPO Caseware'!G:G,'NPO Caseware'!H:H) -> HCLLP WP | H81: =_xlfn.XLOOKUP(F81,'NPO Caseware'!G:G,'NPO Caseware'!I:I) -> Caseview | L81: time_static | M81: confirmation procedure/template — standard
A82: PL-12-7-1 | D82: PL Section | E82: Planning Section | F82: Debt Confirmation #2 Template | G82: =_xlfn.XLOOKUP(F82,'NPO Caseware'!G:G,'NPO Caseware'!H:H) -> HCLLP WP | H82: =_xlfn.XLOOKUP(F82,'NPO Caseware'!G:G,'NPO Caseware'!I:I) -> Caseview | L82: time_static | M82: confirmation procedure/template — standard
A83: PL-12-8 | D83: PL Section | E83: Planning Section | F83: Legal Representation Letter #1 (Client Endorsed) | G83: =_xlfn.XLOOKUP(F83,'NPO Caseware'!G:G,'NPO Caseware'!H:H) -> HCLLP WP | H83: =_xlfn.XLOOKUP(F83,'NPO Caseware'!G:G,'NPO Caseware'!I:I) -> Caseview | L83: time_static | M83: Planning — standard procedure by default (section default)
A84: PL-12-8-1 | D84: PL Section | E84: Planning Section | F84: Legal Representation Letter #1 Template | G84: =_xlfn.XLOOKUP(F84,'NPO Caseware'!G:G,'NPO Caseware'!H:H) -> HCLLP WP | H84: =_xlfn.XLOOKUP(F84,'NPO Caseware'!G:G,'NPO Caseware'!I:I) -> Caseview | L84: time_static | M84: template — rollforward, standard structure
A85: PL-12-9 | D85: PL Section | E85: Planning Section | F85: Legal Representation Letter #2 (Client Endorsed) | G85: =_xlfn.XLOOKUP(F85,'NPO Caseware'!G:G,'NPO Caseware'!H:H) -> HCLLP WP | H85: =_xlfn.XLOOKUP(F85,'NPO Caseware'!G:G,'NPO Caseware'!I:I) -> Caseview | L85: time_static | M85: Planning — standard procedure by default (section default)
A86: PL-12-9-1 | D86: PL Section | E86: Planning Section | F86: Legal Representation Letter #2 Template | G86: =_xlfn.XLOOKUP(F86,'NPO Caseware'!G:G,'NPO Caseware'!H:H) -> HCLLP WP | H86: =_xlfn.XLOOKUP(F86,'NPO Caseware'!G:G,'NPO Caseware'!I:I) -> Caseview | L86: time_static | M86: template — rollforward, standard structure
... A90: PL-12-13 | D90: PL Section | E90: Planning Section | F90: Fraud Risk and Related Party Questionnaire Template #4 | G90: =_xlfn.XLOOKUP(F90,'NPO Caseware'!G:G,'NPO Caseware'!H:H) -> HCLLP WP | H90: =_xlfn.XLOOKUP(F90,'NPO Caseware'!G:G,'NPO Caseware'!I:I) -> Word | L90: time_static | M90: fraud procedure — standard
A91: PL-13 | D91: PL Section | E91: Planning Section | F91: Additional General Planning Procedures for an Initial Audit | G91: =_xlfn.XLOOKUP(F91,'NPO Caseware'!G:G,'NPO Caseware'!H:H) -> PPC | H91: =_xlfn.XLOOKUP(F91,'NPO Caseware'!G:G,'NPO Caseware'!I:I) -> Word | I91: NPO-IA-10 | J91: Use only if this is a first year audit for Harshwal & CO/Blue Arrow CPAs | L91: time_static | M91: Planning — standard procedure by default (section default)
A92: PL-13-1 | D92: PL Section | E92: Planning Section | F92: Request for Predecessor Auditor to Release Information to Successor Auditor (Signed by Client) | G92: =_xlfn.XLOOKUP(F92,'NPO Caseware'!G:G,'NPO Caseware'!H:H) -> PPC | H92: =_xlfn.XLOOKUP(F92,'NPO Caseware'!G:G,'NPO Caseware'!I:I) -> Word | I92: NPO-CL-13.1 | J92: Use only if this is a first year audit for Harshwal & CO/Blue Arrow CPAs | L92: time_static | M92: Planning — standard procedure by default (section default)
A93: PL-13-2 | D93: PL Section | E93: Planning Section | F93: Predecessor Auditor Questionnaire Response | G93: =_xlfn.XLOOKUP(F93,'NPO Caseware'!G:G,'NPO Caseware'!H:H) -> PBC | H93: =_xlfn.XLOOKUP(F93,'NPO Caseware'!G:G,'NPO Caseware'!I:I) -> Word | J93: Use only if this is a first year audit for Harshwal & CO/Blue Arrow CPAs | L93: time_static | M93: Planning — standard procedure by default (section default)
A94: PL-13-3 | D94: PL Section | E94: Planning Section | F94: Predecessor Auditor Workpaper Review Memo | G94: =_xlfn.XLOOKUP(F94,'NPO Caseware'!G:G,'NPO Caseware'!H:H) -> HCLLP WP | H94: =_xlfn.XLOOKUP(F94,'NPO Caseware'!G:G,'NPO Caseware'!I:I) -> Word | J94: Use only if this is a first year audit for Harshwal & CO/Blue Arrow CPAs | L94: timeless | M94: review memo — methodology
A95: IC-1 | D95: IC Section | E95: Internal Control Section | F95: Understanding and Evaluating the System of Internal Control | G95: =_xlfn.XLOOKUP(F95,'NPO Caseware'!G:G,'NPO Caseware'!H:H) -> PPC | H95: =_xlfn.XLOOKUP(F95,'NPO Caseware'!G:G,'NPO Caseware'!I:I) -> Word | I95: ALG-CX-4.1 | L95: time_static | M95: IC — standard procedure by default (section default)
A96: IC-2 | D96: IC Section | E96: Internal Control Section | F96: Internal Control Documentation - Financial Close and Reporting and Significant Transaction Classes | G96: =_xlfn.XLOOKUP(F96,'NPO Caseware'!G:G,'NPO Caseware'!H:H) -> PPC | H96: =_xlfn.XLOOKUP(F96,'NPO Caseware'!G:G,'NPO Caseware'!I:I) -> Word | I96: ALG-CX-4.2.1 | L96: time_static | M96: IC — standard procedure by default (section default)
A97: IC-2-1 | D97: IC Section | E97: Internal Control Section | F97: Internal Control Documentation - IT Environment and General IT Controls | G97: =_xlfn.XLOOKUP(F97,'NPO Caseware'!G:G,'NPO Caseware'!H:H) -> PPC | H97: =_xlfn.XLOOKUP(F97,'NPO Caseware'!G:G,'NPO Caseware'!I:I) -> Word | I97: ALG-CX-4.2.2 | L97: time_static | M97: IC — standard procedure by default (section default)
A98: IC-2-3 | D98: IC Section | E98: Internal Control Section | F98: Internal Control Documentation - Evaluation of Design and Implementation of Identified Controls | G98: =_xlfn.XLOOKUP(F98,'NPO Caseware'!G:G,'NPO Caseware'!H:H) -> PPC | H98: =_xlfn.XLOOKUP(F98,'NPO Caseware'!G:G,'NPO Caseware'!I:I) -> Word | I98: ALG-CX-4.2.3 | L98: time_static | M98: IC — standard procedure by default (section default)
A99: IC-3 | D99: IC Section | E99: Internal Control Section | F99: Entity-level Control Form for Control Environment | G99: =_xlfn.XLOOKUP(F99,'NPO Caseware'!G:G,'NPO Caseware'!H:H) -> PPC | H99: =_xlfn.XLOOKUP(F99,'NPO Caseware'!G:G,'NPO Caseware'!I:I) -> Word | I99: ALG-CX-5.1 | L99: time_static | M99: IC — standard procedure by default (section default)
A100: IC-3-1 | D100: IC Section | E100: Internal Control Section | F100: Entity-level Control Form for Risk Assessment | G100: =_xlfn.XLOOKUP(F100,'NPO Caseware'!G:G,'NPO Caseware'!H:H) -> PPC | H100: =_xlfn.XLOOKUP(F100,'NPO Caseware'!G:G,'NPO Caseware'!I:I) -> Word | I100: ALG-CX-5.2 | L100: time_static | M100: risk assessment template — standard procedure
A101: IC-3-2 | D101: IC Section | E101: Internal Control Section | F101: Entity-level Control Form for Information and Communication | G101: =_xlfn.XLOOKUP(F101,'NPO Caseware'!G:G,'NPO Caseware'!H:H) -> PPC | H101: =_xlfn.XLOOKUP(F101,'NPO Caseware'!G:G,'NPO Caseware'!I:I) -> Word | I101: ALG-CX-5.3 | L101: time_static | M101: IC — standard procedure by default (section default)
A102: IC-3-3 | D102: IC Section | E102: Internal Control Section | F102: Entity-Level Control Form for Monitoring | G102: =_xlfn.XLOOKUP(F102,'NPO Caseware'!G:G,'NPO Caseware'!H:H) -> PPC | H102: =_xlfn.XLOOKUP(F102,'NPO Caseware'!G:G,'NPO Caseware'!I:I) -> Word | I102: ALG-CX-5.4 | L102: time_static | M102: IC — standard procedure by default (section default)
A103: IC-3-4 | D103: IC Section | E103: Internal Control Section | F103: Entity-level Control Form for General IT Controls | G103: =_xlfn.XLOOKUP(F103,'NPO Caseware'!G:G,'NPO Caseware'!H:H) -> PPC | H103: =_xlfn.XLOOKUP(F103,'NPO Caseware'!G:G,'NPO Caseware'!I:I) -> Word | I103: ALG-CX-5.5 | L103: time_static | M103: IC — standard procedure by default (section default)
...

Sheet NPO Caseware
B2: WP Index ID | C2: Process Flow | D2: Process Flow-2 | E2: Type | F2: FS Section | G2: Document Name | H2: Source | I2: File Format | J2: SOP | K2: Mapping | L2: PPC Form Reference | M2: Notes | N2: SOP prepared | O2: Time Bucket | P2: Rationale | Q2: Audit Manager Override | R2: Audit Reviewer Note
B3: FS-FINAL | C3: Reporting | D3: Financial Statement and Deliverables Review | E3: FS Section | F3: Financial Statements and Deliverables Section | G3: Final PDF Copy of the Audited Financial Statements | H3: HCLLP WP | I3: PDF | J3: Needed | O3: time_static | P3: FS draft/final — FS layout stable
B4: FS-CV | C4: Reporting | D4: Financial Statement and Deliverables Review | E4: FS Section | F4: Financial Statements and Deliverables Section | G4: Working Copy of the CaseView Financial Statements | H4: HCLLP WP | I4: PDF | J4: Needed | O4: time_static | P4: CaseView FS working copy — layout stable
B5: FS-CV-1 | C5: Reporting | D5: Financial Statement and Deliverables Review | E5: FS Section | F5: Financial Statements and Deliverables Section | G5: Cash Flow Worksheet (if applicable) | H5: HCLLP WP | I5: Excel | J5: Needed | O5: time_static | P5: cash flow worksheet — format stable
B6: FS-PROG | C6: Reporting | D6: Financial Statement and Deliverables Review | E6: FS Section | F6: Financial Statements and Deliverables Section | G6: Audit Program for General Auditing and Completion Procedures | H6: PPC | I6: Word | J6: Needed | L6: NPO-AP-20 | O6: time_static | P6: audit program — standard procedure
B7: FS-PROG-1 | C7: Reporting | D7: Financial Statement and Deliverables Review | E7: FS Section | F7: Financial Statements and Deliverables Section | G7: Additional General Auditing and Completion Procedures for an Initial Audit | H7: PPC | I7: Word | J7: Needed | L7: NPO-IA-20 | M7: Use only if this is a first year audit for Harshwal & CO/Blue Arrow CPAs | O7: time_static | P7: FS deliverables — default standard procedure (section default)
B8: FS-1 | C8: Final Stage | D8: Financial Statement and Deliverables Review | E8: FS Section | F8: Financial Statements and Deliverables Section | G8: Disclosure Checklist | H8: PPC | I8: Word | J8: Needed | L8: NPO-CX-13 | O8: time_static | P8: disclosure checklist — slowly evolving
B9: FS-2 | C9: Reporting | D9: Management Letters | E9: FS Section | F9: Financial Statements and Deliverables Section | G9: Management Representation Letter (Client Endorsed) | H9: PBC | I9: PDF | J9: NA | O9: time_static | P9: MRL template — standard
B10: FS-2-1 | C10: Reporting | D10: Management Letters | E10: FS Section | F10: Financial Statements and Deliverables Section | G10: Management Representation Letter Template | H10: PPC | I10: Word | J10: Needed | L10: NPO-CL-3.1 | O10: time_static | P10: MRL template — standard
B11: FS-3 | C11: Planning Stage | D11: Information Gathering | E11: FS Section | F11: Financial Statements and Deliverables Section | G11: Legal Representation Letter (Returned Response from Attorney) | H11: HCLLP WP | I11: PDF | J11: Needed | O11: time_static | P11: FS deliverables — default standard procedure (section default)
B12: FS-4 | C12: Final Stage | D12: Exit Conference | E12: FS Section | F12: Financial Statements and Deliverables Section | G12: Communication to Those Charged with Governance at Conclusion (Final PDF Copy provided to Client) | H12: HCLLP WP | I12: PDF | J12: NA | O12: time_static | P12: FS draft/final — FS layout stable
B13: FS-4-1 | C13: Reporting | D13: Exit Conference | E13: FS Section | F13: Financial Statements and Deliverables Section | G13: Communication to Those Charged with Governance at Conclusion Template | H13: PPC | I13: Word | J13: Needed | L13: NPO-CL-5.2 | O13: time_static | P13: TCWG comm — standard
B14: FS-5 | C14: Reporting | D14: Exit Conference | E14: FS Section | F14: Financial Statements and Deliverables Section | G14: Audit Presentation PowerPoint | H14: HCLLP WP | I14: PPT | J14: Needed | O14: time_static | P14: FS deliverables — default standard procedure (section default)
B15: FS-6 | C15: Evidence Evaluation | D15: Analytics | E15: FS Section | F15: Financial Statements and Deliverables Section | G15: Final Analytical Procedures | H15: HCLLP WP | I15: Excel | J15: Needed | O15: time_static | P15: substantive procedure — standard
B16: FS-7 | C16: Reporting | D16: Management Letters | E16: FS Section | F16: Financial Statements and Deliverables Section | G16: Estimates Identification and Retrospective Review | H16: PPC | I16: Word | J16: Needed | L16: NPO-CX-3.6 | O16: time_static | P16: FS deliverables — default standard procedure (section default)
B17: FS-8 | C17: Reporting | D17: Financial Statement and Deliverables Review | E17: FS Section | F17: Financial Statements and Deliverables Section | G17: Supervision, Review and Approval Form | H17: PPC | I17: Word | J17: Needed | L17: NPO-CX-14 | O17: time_static | P17: supervision/review form — standard
B18: FS-9 | C18: Evidence Evaluation | D18: Analytics | E18: FS Section | F18: Financial Statements and Deliverables Section | G18: Retirment Plan Employee and Employer Contribution Report - Footnote Support | H18: PBC | I18: PDF | J18: NA | O18: time_static | P18: FS deliverables — default standard procedure (section default)
B19: FS-9-1 | C19: Reporting | D19: Financial Statement Review | E19: FS Section | F19: Financial Statements and Deliverables Section | G19: Additional FS Footnote Support #2 | H19: PBC | I19: PDF | J19: NA | O19: time_static | P19: FS deliverables — default standard procedure (section default)
B20: FS-9-2 | C20: Reporting | D20: Financial Statement Review | E20: FS Section | F20: Financial Statements and Deliverables Section | G20: Additional FS Footnote Support #3 | H20: PBC | I20: PDF | J20: NA | O20: time_static | P20: FS deliverables — default standard procedure (section default)
B21: ML-1 | C21: Final Stage | D21: Exit Conference | E21: ML Section | F21: Management Advisory Letter and Findings Section | G21: Schedule of Findings and Questioned Costs | H21: HCLLP WP | I21: Caseview | J21: Needed | O21: time_static | P21: questioned costs listing — format stable
B22: ML-2 | C22: Final Stage | D22: Exit Conference | E22: ML Section | F22: Management Advisory Letter and Findings Section | G22: Corrective Action Plan (Provided by Client) | H22: PBC | I22: Word | J22: NA | O22: time_static | P22: ML/findings — finding structure procedural (section default)
B23: ML-3 | C23: Final Stage | D23: Exit Conference | E23: ML Section | F23: Management Advisory Letter and Findings Section | G23: Inventory Tracking Listing of Findings and Questioned Costs - Financial Statement Findings | H23: HCLLP WP | I23: Caseview | J23: Needed | O23: time_static | P23: questioned costs listing — format stable
B24: ML-3-1 | C24: Final Stage | D24: Exit Conference | E24: ML Section | F24: Management Advisory Letter and Findings Section | G24: Inventory Tracking Listing of Findings and Questioned Costs - Federal Award Findings | H24: HCLLP WP | I24: Caseview | J24: Needed | O24: time_static | P24: questioned costs listing — format stable
B25: ML-4 | C25: Reporting | D25: Audit Findings | E25: ML Section | F25: Management Advisory Letter and Findings Section | G25: Control Deficiency Evaluation Worksheet | H25: PPC | I25: Word | J25: Needed | L25: NPO-CX-15.1 | O25: time_static | P25: IC evaluation matrix — standard
B26: ML-5 | E26: ML Section | F26: Management Advisory Letter and Findings Section | G26: Noncompliance Evaluation Form - Federal Award Programs | H26: PPC | I26: Word | J26: Needed | L26: NPO-CX-12.3 | O26: time_static | P26: ML/findings — finding structure procedural (section default)
B27: ML-6 | C27: Pre- Engagement Phase | D27: Risk Assessment | E27: ML Section | F27: Management Advisory Letter and Findings Section | G27: Status of Prior Year Findings and Questioned Costs | H27: HCLLP WP | I27: Word | J27: Needed | O27: time_static | P27: questioned costs listing — format stable
B28: TB-1 | C28: Planning Stage | D28: Information Gathering | E28: TB Section | F28: Trial Balance Section | G28: Trial Balance - Final (Automatic CaseWare Document) | H28: HCLLP WP | I28: Caseview | J28: NA | O28: time_static | P28: TB — mapping stable 4-5 yrs
B29: TB-2 | C29: Planning Stage | D29: Information Gathering | E29: TB Section | F29: Trial Balance Section | G29: Trial Balance Import File (client provided and formatted for import) | H29: HCLLP WP | I29: Excel | J29: Needed | O29: time_static | P29: TB — mapping stable 4-5 yrs
B30: TB-3 | C30: Detailed Audit Procedures | D30: Testing procedures | E30: TB Section | F30: Trial Balance Section | G30: Adjusting Journal Entries Report (Automatic CaseWare Document) | H30: HCLLP WP | I30: LeadSheet | J30: NA | O30: time_static | P30: AJE/RJE — JE listing format stable
B31: TB-4 | C31: Detailed Audit Procedures | D31: Testing procedures | E31: TB Section | F31: Trial Balance Section | G31: Reclassifying Journal Entries Report (Automatic CaseWare Document) | H31: HCLLP WP | I31: LeadSheet | J31: NA | O31: time_static | P31: TB section — format/mapping stable 4-5 yrs (section default)
B32: TB-5 | C32: Detailed Audit Procedures | D32: Testing procedures | E32: TB Section | F32: Trial Balance Section | G32: Passed Adjusting Journal Entries Report (Automatic CaseWare Document) | H32: HCLLP WP | I32: LeadSheet | J32: NA | O32: time_static | P32: AJE/RJE — JE listing format stable
B33: TB-6 | C33: Reporting | D33: Audit Findings | E33: TB Section | F33: Trial Balance Section | G33: Audit Difference Evaluation Form | H33: PPC | I33: Word | J33: Needed | L33: NPO-CX-12.2 | O33: time_static | P33: audit difference eval — format stable
B34: PL-PROG | C34: Planning Stage | D34: Completion (Planning Stage) | E34: PL Section | F34: Planning Section | G34: Audit Program for General Planning Procedures | H34: PPC | I34: Word | J34: Needed | L34: NPO-AP-10 | O34: time_static | P34: audit program — standard procedure
A35: OK | B35: PL-1 | C35: Pre- Engagement Phase | D35: Engagement Independence Evaluation | E35: PL Section | F35: Planning Section | G35: Engagement Acceptance and Continuation Form | H35: PPC | I35: Word | J35: Needed | L35: NPO-CX-1.1 | O35: time_static | P35: engagement procedure — standard
B36: PL-2 | C36: Pre- Engagement Phase | D36: Engagement Independence Evaluation | E36: PL Section | F36: Planning Section | G36: Evaluating Independence - Yellowbook and GAAS Audits | H36: PPC | I36: Word | J36: Needed | L36: NPO-CX-1.3 | O36: time_static | P36: independence checklist — standard procedure
B37: PL-3 | C37: Pre- Engagement Phase | D37: Engagement Independence Evaluation | E37: PL Section | F37: Planning Section | G37: Continuing Professional Education Documentation Form | H37: PPC | I37: Word | J37: Needed | L37: NPO-CX-1.4 | O37: time_static | P37: Planning — standard procedure by default (section default)
A38: OK | B38: PL-4 | C38: Pre- Engagement Phase | D38: Engagement letter | E38: PL Section | F38: Planning Section | G38: Engagement Letter (Client endorsed) | H38: HCLLP WP | I38: PDF | J38: NA | O38: time_static | P38: engagement procedure — standard
A39: OK | B39: PL-4-1 | C39: Pre- Engagement Phase | D39: Engagement letter | E39: PL Section | F39: Planning Section | G39: Engagement Letter template | H39: HCLLP WP | I39: Caseview | J39: Needed | O39: time_static | P39: engagement procedure — standard
B40: PL-5 | C40: Planning Stage | D40: Client Communication (Planning Stage) | E40: PL Section | F40: Planning Section | G40: Communication to Those Charged with Governance During Planning | H40: PPC | I40: Word | J40: Needed | L40: NPO-CX-5.1 | O40: time_static | P40: TCWG comm — standard
B41: PL-6 | C41: Planning Stage | D41: Information Gathering | E41: PL Section | F41: Planning Section | G41: Understanding the Entity and Identifying Risks | H41: PPC | I41: Word | J41: Needed | L41: NPO-CX-3.1 | O41: time_static | P41: understanding entity — standard
B42: PL-6-1 | C42: Planning Stage | D42: Information Gathering | E42: PL Section | F42: Planning Section | G42: Listing of Board Members including contact information | H42: PBC | I42: PDF | J42: NA | O42: time_static | P42: Planning — standard procedure by default (section default)
B43: PL-6-2 | C43: Planning Stage | D43: Information Gathering | E43: PL Section | F43: Planning Section | G43: Listing of Management and Key Personnel including contact information | H43: PBC | I43: PDF | J43: NA | O43: time_static | P43: Planning — standard procedure by default (section default)
B44: PL-6-3 | C44: Planning Stage | D44: Information Gathering | E44: PL Section | F44: Planning Section | G44: Listing of Legal Counsel including contact information | H44: PBC | I44: PDF | J44: NA | O44: time_static | P44: Planning — standard procedure by default (section default)
B45: PL-7 | C45: Planning Stage | D45: Information Gathering | E45: PL Section | F45: Planning Section | G45: Checklist of Tax-Related Considerations in a Nonprofit Orgranization Audit | H45: HCLLP WP | I45: Caseview | J45: Needed | L45: NPO-CX-11.7 | O45: time_static | P45: checklist — standard procedure
B46: PL-8 | C46: Planning Stage | D46: Internal Control and Risk Assessment | E46: PL Section | F46: Planning Section | G46: Financial Statement Materiality Worksheet for Planning Purposes | H46: HCLLP WP | I46: Caseview | J46: Needed | L46: NPO-CX-2.1 | O46: time_sensitive | P46: materiality calc — benchmark %/threshold $ that updates
B47: PL-8-1 | E47: PL Section | F47: Planning Section | G47: Financial Statement Materiality Worksheet - Final Assessment at Conclusion | H47: HCLLP WP | I47: Caseview | J47: Needed | L47: NPO-CX-2.1 | O47: time_sensitive | P47: materiality calc — benchmark %/threshold $ that updates
B48: PL-9 | C48: Planning Stage | D48: Information Gathering | E48: PL Section | F48: Planning Section | G48: Audit Program for Minutes, Contracts, Ordinances, and Laws | H48: PPC | I48: Caseview | J48: Needed | L48: NPO-AP-40 | O48: time_static | P48: audit program — standard procedure
B49: PL-9-1 | C49: Planning Stage | D49: Information Gathering | E49: PL Section | F49: Planning Section | G49: Review of Board Minutes Workpaper | H49: HCLLP WP | I49: Word | J49: Needed | O49: time_static | P49: Planning — standard procedure by default (section default)
B50: PL-10 | C50: Evidence Evaluation | D50: Analytics | E50: PL Section | F50: Planning Section | G50: Preliminary Analytical - (CaseWare Automatic Document) | H50: HCLLP WP | I50: LeadSheet/Excel | J50: Needed | O50: time_static | P50: substantive procedure — standard
B51: PL-11 | C51: Pre- Engagement Phase | D51: Client Communication (Pre-Engagement Phase) | E51: PL Section | F51: Planning Section | G51: PBC List | H51: HCLLP WP | I51: Excel | J51: Needed | O51: time_static | P51: PBC list — standard
B52: PL-12 | C52: Planning Stage | D52: Client Communication (Planning Stage) | E52: PL Section | F52: Planning Section | G52: Confirmation Control Log (Standard Workpaper) | H52: HCLLP WP | I52: Caseview | J52: Needed | M52: Remember: AU-C 330.20 requires external confirmations for AR to be sent unless: | O52: time_static | P52: confirmation procedure/template — standard
B53: PL-12-1 | C53: Planning Stage | D53: Information Gathering | E53: PL Section | F53: Planning Section | G53: Cash Confirmation #1 (Client Endorsed) | H53: HCLLP WP | I53: Caseview | J53: NA | M53: 1) Balance is Immaterial | O53: time_static | P53: confirmation procedure/template — standard
B54: PL-12-1-1 | C54: Planning Stage | D54: Client Communication (Planning Stage) | E54: PL Section | F54: Planning Section | G54: Cash Confirmation #1 Template | H54: HCLLP WP | I54: Caseview | J54: Needed | M54: 2) External Confirmations would be ineffective | O54: time_static | P54: confirmation procedure/template — standard
B55: PL-12-2 | C55: Planning Stage | D55: Information Gathering | E55: PL Section | F55: Planning Section | G55: Cash Confirmation #2 (Client Endorsed) | H55: HCLLP WP | I55: Caseview | J55: NA | M55: 3) The Auditor's risk of material misstatement is low and other planned procedures address | O55: time_static | P55: confirmation procedure/template — standard
B56: PL-12-2-1 | C56: Planning Stage | D56: Client Communication (Planning Stage) | E56: PL Section | F56: Planning Section | G56: Cash Confirmation #2 Template | H56: HCLLP WP | I56: Caseview | J56: Needed | M56: the assessed risk. | O56: time_static | P56: confirmation procedure/template — standard
B57: PL-12-3 | C57: Planning Stage | D57: Information Gathering | E57: PL Section | F57: Planning Section | G57: AR Confirmation #1 (Client Endorsed) | H57: HCLLP WP | I57: Caseview | J57: NA | M57: Document witin PL-12 the reason for not sending AR confirmations if they are not | O57: time_static | P57: confirmation procedure/template — standard
B58: PL-12-3-1 | C58: Planning Stage | D58: Client Communication (Planning Stage) | E58: PL Section | F58: Planning Section | G58: AR Confirmation #1 Template | H58: HCLLP WP | I58: Caseview | J58: Needed | M58: sent. | O58: time_static | P58: confirmation procedure/template — standard
B59: PL-12-4 | C59: Planning Stage | D59: Information Gathering | E59: PL Section | F59: Planning Section | G59: AR Confirmation #2 (Client Endorsed) | H59: HCLLP WP | I59: Caseview | J59: NA | O59: time_static | P59: confirmation procedure/template — standard
B60: PL-12-4-1 | C60: Planning Stage | D60: Client Communication (Planning Stage) | E60: PL Section | F60: Planning Section | G60: AR Confirmation #2 Template | H60: HCLLP WP | I60: Caseview | J60: Needed | O60: time_static | P60: confirmation procedure/template — standard
B61: PL-12-5 | C61: Planning Stage | D61: Information Gathering | E61: PL Section | F61: Planning Section | G61: Investments Confirmation #1 (Client Endorsed) | H61: HCLLP WP | I61: Caseview | J61: NA | O61: time_static | P61: confirmation procedure/template — standard
B62: PL-12-5-1 | C62: Planning Stage | D62: Client Communication (Planning Stage) | E62: PL Section | F62: Planning Section | G62: Investments Confirmation #1 Template | H62: HCLLP WP | I62: Caseview | J62: Needed | O62: time_static | P62: confirmation procedure/template — standard
B63: PL-12-6 | C63: Planning Stage | D63: Information Gathering | E63: PL Section | F63: Planning Section | G63: Debt Confirmation #1 (Client Endorsed) | H63: HCLLP WP | I63: Caseview | J63: NA | O63: time_static | P63: confirmation procedure/template — standard
B64: PL-12-6-1 | C64: Planning Stage | D64: Client Communication (Planning Stage) | E64: PL Section | F64: Planning Section | G64: Debt Confirmation #1 Template | H64: HCLLP WP | I64: Caseview | J64: Needed | O64: time_static | P64: confirmation procedure/template — standard
B65: PL-12-7 | C65: Planning Stage | D65: Information Gathering | E65: PL Section | F65: Planning Section | G65: Debt Confirmation #2 (Client Endorsed) | H65: HCLLP WP | I65: Caseview | J65: NA | O65: time_static | P65: confirmation procedure/template — standard
B66: PL-12-7-1 | C66: Planning Stage | D66: Client Communication (Planning Stage) | E66: PL Section | F66: Planning Section | G66: Debt Confirmation #2 Template | H66: HCLLP WP | I66: Caseview | J66: Needed | O66: time_static | P66: confirmation procedure/template — standard
B67: PL-12-8 | C67: Planning Stage | D67: Information Gathering | E67: PL Section | F67: Planning Section | G67: Legal Representation Letter #1 (Client Endorsed) | H67: HCLLP WP | I67: Caseview | J67: NA | O67: time_static | P67: Planning — standard procedure by default (section default)
B68: PL-12-8-1 | C68: Planning Stage | D68: Information Gathering | E68: PL Section | F68: Planning Section | G68: Legal Representation Letter #1 Template | H68: HCLLP WP | I68: Caseview | J68: Needed | O68: time_static | P68: template — rollforward, standard structure
B69: PL-12-9 | C69: Planning Stage | D69: Information Gathering | E69: PL Section | F69: Planning Section | G69: Legal Representation Letter #2 (Client Endorsed) | H69: HCLLP WP | I69: Caseview | J69: NA | O69: time_static | P69: Planning — standard procedure by default (section default)
B70: PL-12-9-1 | C70: Planning Stage | D70: Information Gathering | E70: PL Section | F70: Planning Section | G70: Legal Representation Letter #2 Template | H70: HCLLP WP | I70: Caseview | J70: NA | O70: time_static | P70: template — rollforward, standard structure
... B74: PL-12-13 | C74: Planning Stage | D74: Client Questionnaires | E74: PL Section | F74: Planning Section | G74: Fraud Risk and Related Party Questionnaire Template #4 | H74: HCLLP WP | I74: Word | J74: NA | O74: time_static | P74: fraud procedure — standard
B75: PL-13 | C75: Pre- Engagement Phase | D75: Engagement letter | E75: PL Section | F75: Planning Section | G75: Additional General Planning Procedures for an Initial Audit | H75: PPC | I75: Word | J75: Needed | L75: NPO-IA-10 | M75: Use only if this is a first year audit for Harshwal & CO/Blue Arrow CPAs | O75: time_static | P75: Planning — standard procedure by default (section default)
B76: PL-13-1 | C76: Pre- Engagement Phase | D76: Client Communication (Pre-Engagement Phase) | E76: PL Section | F76: Planning Section | G76: Request for Predecessor Auditor to Release Information to Successor Auditor (Signed by Client) | H76: PPC | I76: Word | J76: Needed | L76: NPO-CL-13.1 | M76: Use only if this is a first year audit for Harshwal & CO/Blue Arrow CPAs | O76: time_static | P76: Planning — standard procedure by default (section default)
B77: PL-13-2 | C77: Pre- Engagement Phase | D77: Client Communication (Pre-Engagement Phase) | E77: PL Section | F77: Planning Section | G77: Predecessor Auditor Questionnaire Response | H77: PBC | I77: Word | J77: NA | M77: Use only if this is a first year audit for Harshwal & CO/Blue Arrow CPAs | O77: time_static | P77: Planning — standard procedure by default (section default)
B78: PL-13-3 | C78: Pre- Engagement Phase | D78: Client Communication (Pre-Engagement Phase) | E78: PL Section | F78: Planning Section | G78: Predecessor Auditor Workpaper Review Memo | H78: HCLLP WP | I78: Word | M78: Use only if this is a first year audit for Harshwal & CO/Blue Arrow CPAs | O78: timeless | P78: review memo — methodology
B79: IC-1 | C79: Planning Stage | D79: Internal Control and Risk Assessment | E79: IC Section | F79: Internal Control Section | G79: Understanding and Evaluating the System of Internal Control | H79: PPC | I79: Word | J79: Needed | L79: NPO-CX-4.1 | O79: time_static | P79: IC — standard procedure by default (section default)
B80: IC-2 | C80: Planning Stage | D80: Internal Control and Risk Assessment | E80: IC Section | F80: Internal Control Section | G80: Internal Control Documentation - Financial Close and Reporting and Significant Transaction Classes | H80: PPC | I80: Word | J80: Needed | L80: NPO-CX-4.2.1 | O80: time_static | P80: IC — standard procedure by default (section default)
B81: IC-2-1 | C81: Planning Stage | D81: Internal Control and Risk Assessment | E81: IC Section | F81: Internal Control Section | G81: Internal Control Documentation - IT Environment and General IT Controls | H81: PPC | I81: Word | J81: Needed | L81: NPO-CX-4.2.2 | O81: time_static | P81: IC — standard procedure by default (section default)
B82: IC-2-3 | C82: Planning Stage | D82: Internal Control and Risk Assessment | E82: IC Section | F82: Internal Control Section | G82: Internal Control Documentation - Evaluation of Design and Implementation of Identified Controls | H82: PPC | I82: Word | J82: Needed | L82: NPO-CX-4.2.3 | O82: time_static | P82: IC — standard procedure by default (section default)
B83: IC-3 | C83: Planning Stage | D83: Internal Control and Risk Assessment | E83: IC Section | F83: Internal Control Section | G83: Entity-level Control Form for Control Environment | H83: PPC | I83: Word | J83: Needed | L83: NPO-CX-5.1 | O83: time_static | P83: IC — standard procedure by default (section default)
B84: IC-3-1 | C84: Planning Stage | D84: Internal Control and Risk Assessment | E84: IC Section | F84: Internal Control Section | G84: Entity-level Control Form for Risk Assessment | H84: PPC | I84: Word | J84: Needed | L84: NPO-CX-5.2 | O84: time_static | P84: risk assessment template — standard procedure
B85: IC-3-2 | C85: Planning Stage | D85: Internal Control and Risk Assessment | E85: IC Section | F85: Internal Control Section | G85: Entity-level Control Form for Information and Communication | H85: PPC | I85: Word | J85: Needed | L85: NPO-CX-5.3 | O85: time_static | P85: IC — standard procedure by default (section default)
B86: IC-3-3 | C86: Planning Stage | D86: Internal Control and Risk Assessment | E86: IC Section | F86: Internal Control Section | G86: Entity-Level Control Form for Monitoring | H86: PPC | I86: Word | J86: Needed | L86: NPO-CX-5.4 | O86: time_static | P86: IC — standard procedure by default (section default)
B87: IC-3-4 | C87: Planning Stage | D87: Internal Control and Risk Assessment | E87: IC Section | F87: Internal Control Section | G87: Entity-level Control Form for General IT Controls | H87: PPC | I87: Word | J87: Needed | L87: NPO-CX-5.5 | O87: time_static | P87: IC — standard procedure by default (section default)
B88: IC-4 | C88: Planning Stage | D88: Internal Control and Risk Assessment | E88: IC Section | F88: Internal Control Section | G88: Control Activities Form for Financial Close and Reporting | H88: PPC | I88: Word | J88: Needed | L88: NPO-CX-5.6 | O88: time_static | P88: IC — standard procedure by default (section default)
B89: IC-4-1 | C89: Planning Stage | D89: Internal Control and Risk Assessment | E89: IC Section | F89: Internal Control Section | G89: Control Activities Form for Cash | H89: PPC | I89: Word | J89: Needed | L89: NPO-CX-5.7 | O89: time_static | P89: IC — standard procedure by default (section default)
B90: IC-4-2 | C90: Planning Stage | D90: Internal Control and Risk Assessment | E90: IC Section | F90: Internal Control Section | G90: Control Activities Form for Support, Receivables, and Receipts | H90: PPC | I90: Word | J90: Needed | L90: NPO-CX-5.9 | O90: time_static | P90: IC — standard procedure by default (section default)
... B101: IC-4-13 | C101: Planning Stage | D101: Internal Control and Risk Assessment | E101: IC Section | F101: Internal Control Section | G101: Control Activities Form for Inventories | H101: PPC | I101: Word | J101: Needed | L101: NPO-CX-5.14 | O101: time_static | P101: IC — standard procedure by default (section default)
B102: IC-5 | C102: Planning Stage | D102: Internal Control and Risk Assessment | E102: IC Section | F102: Internal Control Section | G102: Internal Control Memo - Financial Close and Reporting | H102: HCLLP WP | I102: Word | J102: Needed | O102: timeless | P102: IC memo — describes how controls work
B103: IC-5-1 | C103: Planning Stage | D103: Internal Control and Risk Assessment | E103: IC Section | F103: Internal Control Section | G103: Internal Control Memo - Cash and Investments | H103: HCLLP WP | I103: Word | J103: Needed | O103: timeless | P103: IC memo — describes how controls work
B104: IC-5-2 | C104: Planning Stage | D104: Internal Control and Risk Assessment | E104: IC Section | F104: Internal Control Section | G104: Internal Control Memo - Support, Receivables, Program Service Fees, and Receipts | H104: HCLLP WP | I104: Word | J104: Needed | O104: timeless | P104: IC memo — describes how controls work
B105: IC-5-3 | C105: Planning Stage | D105: Internal Control and Risk Assessment | E105: IC Section | F105: Internal Control Section | G105: Internal Control Memo - Expenses for Program and Supporting Services and Accounts Payable and Other Liabilities | H105: HCLLP WP | I105: Word | J105: Needed | O105: timeless | P105: IC memo — describes how controls work
B106: IC-5-4 | C106: Planning Stage | D106: Internal Control and Risk Assessment | E106: IC Section | F106: Internal Control Section | G106: Internal Control Memo - Payroll and Related Liabilities | H106: HCLLP WP | I106: Word | J106: Needed | O106: timeless | P106: IC memo — describes how controls work
B107: IC-5-5 | C107: Planning Stage | D107: Internal Control and Risk Assessment | E107: IC Section | F107: Internal Control Section | G107: Internal Control Memo - Net Assets | H107: HCLLP WP | I107: Word | J107: Needed | O107: timeless | P107: IC memo — describes how controls work
B108: IC-5-6 | C108: Planning Stage | D108: Internal Control and Risk Assessment | E108: IC Section | F108: Internal Control Section | G108: Internal Control Memo - Grants and Similar Programs | H108: HCLLP WP | I108: Word | J108: Needed | O108: timeless | P108: IC memo — describes how controls work
B109: IC-5-7 | C109: Planning Stage | D109: Internal Control and Risk Assessment | E109: IC Section | F109: Internal Control Section | G109: Internal Control Memo - Property and Equipment | H109: HCLLP WP | I109: Word | J109: Needed | O109: timeless | P109: IC memo — describes how controls work
B110: IC-5-8 | C110: Planning Stage | D110: Internal Control and Risk Assessment | E110: IC Section | F110: Internal Control Section | G110: Internal Control Memo - Debt and Other Liabilities | H110: HCLLP WP | I110: Word | J110: Needed | O110: timeless | P110: IC memo — describes how controls work
B111: IC-6 | C111: Planning Stage | D111: Internal Control and Risk Assessment | E111: IC Section | F111: Internal Control Section | G111: Walkthrough Testing over Financial Close and Reporting | H111: HCLLP WP | I111: Word | J111: Needed | O111: time_static | P111: walkthrough — standard procedure
B112: IC-6-1 | C112: Planning Stage | D112: Internal Control and Risk Assessment | E112: IC Section | F112: Internal Control Section | G112: Walkthrough Testing over Cash and Investments | H112: HCLLP WP | I112: Word | J112: Needed | O112: time_static | P112: walkthrough — standard procedure
B113: IC-6-2 | C113: Planning Stage | D113: Internal Control and Risk Assessment | E113: IC Section | F113: Internal Control Section | G113: Walkthrough Testing over Support, Receivables, Program Service Fees, and Receipts | H113: HCLLP WP | I113: Word | J113: Needed | O113: time_static | P113: walkthrough — standard procedure
... B123: IC-9-1 | C123: Planning Stage | D123: Internal Control and Risk Assessment | E123: IC Section | F123: Internal Control Section | G123: Information Technology Internal Control Questionnaire - Template sent to Client | H123: HCLLP WP | I123: Word | J123: Needed | O123: time_static | P123: ICQ — standard
...

Sheet Process Flow 1
A2: 1 | B2: Pre- Engagement Phase
B4: Client Evaluation and Acceptance | D4: Engagement letter | F4: Engagement Independence Evaluation | H4: Client Communication (Pre-Engagement Phase) | L4: Tools:
L5: PPC Checkpoint
B6: Identify potential client | D6: Select the appropriate EL template based on entity type. | F6: Assess firm personnel resources and determine engagement team. | H6: Conduct Client Kick-off Meeting via Zoom or at the client’s location. | L6: EL Bot
B7: Conduct internal discussions to determine engagement feasibility. | D7: Customize the letter via Caseview or EL bot | F7: Perform an independence check of engagement team before starting the audit. Done via checklist | H7: Introduce the Audit Team to the client. | L7: Monday.com
B8: Gather preliminary client information, including key risk factors such as cash flow issues, pending law suits. | D8: Define audit scope, responsibilities, and reporting framework. | F8: Document findings and approvals using the Engagement Independence Compliance form. | H8: Review Prior Year (PY) Report for reference. | L8: Suralink (E-signature)
B9: Evaluate the client’s background, industry, and risk profile. | D9: Confirm management’s responsibility for financial statements | F9: Review client relationships and past services to identify potential threats to independence. | H9: Discuss Audit Plan & Timeline with client. | L9: Suralink
B10: Assess independence, potential conflicts, and compliance requirements. (Firm-wide analysis) | D10: Confirm audit timelines, deliverables, and communication protocols. | F10: Assess nonattest services and evaluate their impact on independence. | H10: Discuss audit deliverables and expectations
B11: Prepare engagement proposal including cost determination | D11: Share the EL draft with the review team and obtain Engagement Partner approval EL for issuance to client. | F11: Obtain Engagement Partner approval for engagement team independence evaluation. | H11: Document the meeting in the Entrance Conference Memo.
B12: Obtain Engagement Partner approval for proposal | D12: Upon Engagement Partner approval send EL to the client via email or Suralink e-signature. | H12: Complete PBC List | R12: S
B13: Submit proposal to potential client. | D13: Receive the signed EL from client management and document and place into Caseware Engagement file. | H13: Obtain Engagement Partner approval for PBC list
H14: Upload PBC list to Suralink and email to client
A20: 2 | B20: Planning Stage
B22: Information Gathering | D22: Client Questionnaires | F22: Internal Control and Risk Assessment | H22: Client Communication (Planning Stage) | J22: Sample Planning and Selection | L22: Completion (Planning) | O22: Tools:
O23: Suralink
B24: Collect necessary documents from the client for audit planning. | D24: Distribute and collect Fraud risk and Related Party Questionnaires from the client. | F24: Document entity level controls | H24: Prepare Communications Letter to Those Charged with Governance During Planning form. (Required Communications) | J24: Determine areas for which sampling for substantive testing is required. | L24: Complete Planning Program | O24: PPC Smart practice Aids
B25: Obtain attorney details contact details, prepare, and send legal confirmation requests; review and document responses. | D25: Assess fraud risks based on questionnaire responses. | F25: Document internal control processes for financial reporting, IT controls, and transaction processing. | H25: Obtain Engagement Partner approval of Planning Communications Letter. | J25: Determine populations for samples. | O25: Internal Questionnaires
B26: Obtain listing of Board/Governance Members and contact information | D26: Identify and evaluate related party transactions for potential conflicts or undisclosed relationships. | F26: Prepare Internal Control Memos and identify key internal controls over significant audit areas such as Disbursements, Payroll, Revenue, and Financial Close. | H26: Send planning communications letter to Goveranance and Management | J26: Plan samples sizes | O26: Confirmation.com
B27: Obtain listing of Management and Key Accounting Staff and contact information | D27: Cross-check responses with financial records and transaction details. | F27: Conduct internal control walkthroughs of key internal controls over the significant transaction cycles. | H27: Prepare confirmation letters to be sent to external parties (attorneys, accounts receivable, depository accounts, investment accounts, etc) | J27: Select samples
B28: Board Minutes - Review and analyze board meeting minutes to capture significant financial and operational decisions and events | D28: Assess and document litigation and contingent liabilities for financial and compliance impact. | F28: Complete Understanding and Evaluating the System of Internal Control form | H28: Provide confirmation letters to client for signature/authorization. | J28: Obtain Engagement Partner approval for sampling methodology and samples selected.
B29: Trial Balance Import - Import and map trial balance(s) received from client. | D29: Document findings and incorporate them into the overall risk assessment. | F29: Determine materiality thresholds by completing the Preliminary Materiality Worksheet. | H29: Prepare Confirmation Control Log documenting dates sent and received from external parties | J29: Send samples to client via email and upload to SURALINK.
B30: Current Year Payment Register - obtain and summarize FY 2025 check register by vendor. Select sample of significant and/or unusual vendors for fraud risk and related party testing. | F30: Perform a Preliminary Analytical Review to identify unusual trends and variances to assist with Risk Assessment and determining the nature, timing and extent of audit procedures to be performed. | H30: Receive confirmation letters back from client.
B31: Trial Balance Import - Import and map trial balance(s) received from client. | F31: Complete Inherent Risk Assessment (IR) through inherent risk assessment forms and fraud inquiries. | H31: Send confirmation letters to external parties.
B32: Complete Understanding the Entity and Identifying Risks form | F32: Determine if internal controls will be tested to support a planned level of control risk less than HIGH.
F33: Complete overall Risk Assessment (RMM) and complete Risk Assessment Summary Form.
F34: Obtain Engagement Partner approval for Risk Assessment.
F35: Prepare audit programs based on overall Risk Assessment
F36: Hold an engagement team discussion with team and ensure Engagement Partner is present.
A41: 3 | B41: Detailed Audit Procedures
B43: Documentation review | D43: Testing procedures | L43: Tools:
L44: CaseWare
L45: PPC templates
B46: Gather and examine financial documents (invoices, receipts, contracts, agreements) for audit assertions like completeness and relevance. | D46: Prepare testwork (TW) files for key financial areas, including revenue, disbursements, payroll, and journal entries.
B47: Verify approvals and authorization for disbursements, payroll, and significant transactions. | D47: Assess internal controls by testing approvals, classifications, and compliance with policies.
B48: Identify missing or inconsistent documentation and request clarifications from the client. | D48: Perform substantive testing by selecting samples and verifying recorded transactions.
B49: Cross check with external confirmations (bank statements, AR and AP confirmation, legal contracts) to validate accuracy. | D49: Analyze trends and variances to detect potential misstatements.
B50: Maintain organized and well referenced audit documentation to support conclusions
A55: 4 | B55: Fieldwork
B57: Team Collaboration | D57: Evidence Collection | F57: Tools:
F58: CaseWare
F59: Suralink
B60: Schedule fieldwork and visit the client’s office to conduct on site audit procedures. | D60: Share Sample Sheet (Excel) with the client for document retrieval.
B61: Perform walkthroughs for key processes, including payroll, revenue, disbursements, and IT. | D61: Review available files for completeness.
B62: Review the Trial Balance to assess account balances and identify key audit areas. | D62: Request missing documents via Suralink
B63: Prepare the Planning Materiality Sheet to set thresholds for testing. | D63: Organize collected evidence on CaseWare for testing.
B64: Pull and share sample lists from the General Ledger with the client for document retrieval.
B65: Conduct on-site sample testing to verify accuracy and compliance.
A72: 5 | B72: Evidence Evaluation
B74: Analytics | D74: Risk Assessment (Re-evaluation) | F74: Tools:
F75: CaseWare
B76: Perform analytical procedures to detect trends, patterns, and fluctuations. | D76: Reassess entity risks based on audit findings using the Risk Assessment Summary Form | F76: Suralink
B77: Investigate significant variances and obtain explanations. | D77: Evaluate internal control effectiveness
B78: Assess key financial ratios for inconsistencies. | D78: Adjust audit procedures if needed
B79: Document findings and conclusions for audit evidence. | D79: Document final risk conclusions
A86: 6 | B86: Reporting
B88: Audit Findings | D88: Financial Statement and Deliverables | F88: Tools:
F89: CaseWare
B90: Review Testwork Conclusion Sections to compile key audit findings. | D90: Update financials and notes based on the audit-adjusted trial balance in caseview. | F90: CaseView
B91: Review Prior Year Audit Findings follow-up | D91: Review and validate key financial statement, and disclosures.
B92: Identify and communicate significant deficiencies to the client. | D92: Ensure proper classification and consistency across all financial documents.
B93: Document CAP (Corrective Action Plan) Response for client-proposed remediation steps. | D93: Ensure documents are Signed off
D94: Conduct a team meeting to discuss challenges
D95: Ensure all necessary adjustments are reflected in the final financial statements
A100: 7 | B100: Final Stage
B102: Exit Conference | D102: Management Letters | F102: Tools:
F103: DocuSign
B104: Conduct the Exit Conference to discuss audit findings, adjustments, and final conclusions with management. | D104: Ensure all review notes are cleared.
B105: Obtain client acknowledgment on key findings and proposed adjustments | D105: Summarize all audit adjustments entries and take client confirmation.
B106: Address final queries or concerns before closing the audit. | D106: Prepare the Summary Audit Difference Evaluation Form (SAD).
B107: Document management responses, corrective actions, and follow-ups | D107: Prepare the disclosure checklist to ensure audit close.
B108: Check all required forms are signed, finalized, | D108: Obtain the Management Representation Letter (MRL) from the client.
B109: Take partner approval before sharing final audited report | D109: Draft the Management Comment Letter with audit observations, recommendations, and improvement areas.
B110: Share the final audit report, audited financial statements, and physical binder (if requested) with the client and obtain acknowledgment. | D110: Issue final invoices and confirm payment.
A116: 8 | B116: Post-Audit
B118: Recommendation Tracking | D118: Future Planning
B119: Discuss key audit takeaways with the client for next year | D119: Update client profile on Monday.com.
B120: Schedule next year’s audit timeline and key deliverables | D120: Roll forward CaseWare file.
D121: Sanitize and archive workpapers.
D122: Document key audit takeaways.
D123: Schedule next year’s planning discussions.

Sheet Automated Process Flow 2
A2: 1 | B2: Pre- Engagement Phase
B4: Automated Client Onboarding | D4: Automated Engagement letters | F4: Automated Risk Assessment | H4: Automation Tools:
H5: PPC Checkpoint- Auto-generates letters
B6: Client details are auto-populated in Monday.com from previous engagements. | D6: EL is generated in CaseView, using predefined templates. | F6: PPC Smart Practice Aids assist with risk assessment | H6: EL Bot- RFP based letter generation
B7: System auto-validates client name, contact, industry, and prior audit history. | D7: The generated EL is reviewed for accuracy before sharing. | F7: Engagement details are selected, and client data auto-fills in PPC Smart Practice Aids. | H7: Monday.com- Automated task tracking
B8: New clients are manually added to CaseWare and Monday.com's database | D8: Share with Onshore audit team and then with the client via DocuSign. | F8: Risk assessment questions are answered, and risks are categorized automatically.
F9: Audit procedures are suggested based on identified risks.
F10: Auto-filled audit program workpapers are generated and linked to CaseWare.
A16: 2 | B16: Planning Stage
B18: Automated Document Collection | D18: AI-Driven Data Analysis | F18: Automated Risk Assessment | H18: Automation Tools:
H19: Suralink- Auto-tracks documents
B20: Documents are requested via the Suralink Portal using the audit prep guide, following the CaseWare folder structure. | D20: Prior-year trial balance (PY TB) is already stored in CaseWare. | F20: A digital questionnaire is shared with the client to collect risk-related information. | H20: PPC Smart Practices Aids
B21: Other pending client documents are requested via Outlook | D21: When the current year trial balance is imported, the preliminary analytical lead sheet auto-generates. | F21: Clients complete and submit the questionnaire, providing details on financial processes, internal controls, and compliance risks. | H21: Automated Risk Assessment
D22: The lead sheet auto-populates prior-year figures, variance amounts, and variance percentages. | F22: Auditors review the completed questionnaire and incorporate identified risks into the audit planning process. | H22: Digital Questionnaires
D23: Unusual fluctuations are identified for further review based on variance analysis.
A29: 3 | B29: Execution Phase
B31: Automated Document Extraction | D31: Automated Reconciliations | F31: Automated testing | H31: Automation Tools:
H32: CaseWare- Auto-calculations
B33: 1. Client-Provided Documents (via Suralink): | D33: Preliminary analytics auto-generate in CaseWare upon trial balance import, using last year’s audited trial balance for comparison | F33: PPC Templates auto-generate sampling selections based on risk criteria. | H33: PPC Templates- Automated Sampling
B34: Client uploads documents to the Suralink PBC list, assigned to specific line items. | F34: CaseWare auto-validates trial balance data for completeness. | H34: Auto Linking to Trial Balance
B35: Suralink highlights new uploads daily for easy tracking. | F35: Duplicate transactions and unusual patterns are flagged for review.
B36: The audit staff reviews, downloads, and organizes files within the appropriate CaseWare document manager folder.
B37: 2. PPC Documents (via PPC Templates & CaseWare)
B38: The required PPC templates and audit programs are extracted directly from the PPC tool during the audit process.
A46: 4 | B46: Evidence Management
B48: Automated Evidence Collection | D48: Automated Documentation | F48: Auto-referencing | H48: Automation Tools:
H49: Suralink-Auto-tracking
B50: Pending item list is imported into Suralink, including audit requests and selected transactions for testing. | D50: Suralink documents are uploaded into CaseWare, mapping to relevant audit workpapers. | F50: CaseWare assigns an automatic file number when a file is added. | H50: CaseWare- Auto-referencing
B51: Client uploads supporting documents for selected items in the assigned audit sections. | D51: Audit workpapers can be dragged from the PPC audit library into CaseWare. | F51: Excel files use formulas to auto-reference the file name as the testwork name. | H51: Automated Evidence tagging
B52: Auditors review uploaded documents and request additional information if necessary. | D52: Testwork files can be copied from other peer client CaseWare files. | F52: PDF files require manual referencing by creating reference boxes.
B53: Status tracking in Suralink helps monitor pending and completed requests. | D53: Documents received via Outlook can be manually dragged into CaseWare. | F53: PPC Word files come with built-in automatic referencing.
B54: Audit confirmations are initiated and tracked through Confirmation.com, streamlining bank, legal, and third-party confirmations. | D54: Confirmations from Confirmation.com can be imported into CaseWare. | F54: Lead sheet references are automatically generated in CaseWare.
D55: Signed documents from DocuSign can be manually added to CaseWare.
A60: 5 | B60: Review Process
B62: Automated Analytics | D62: Auto-generated insights | F62: Automated issue tracking | H62: Automation Tools:
H63: CaseWare- Auto-analytics
B64: Preliminary analytics auto-generate in CaseWare upon trial balance import, using last year’s audited trial balance for comparison. | D64: CaseView auto-populates financial statements and MD&A using imported trial balance data. | F64: Reviewers can add comments on each testwork file, tagging team members for follow-ups. | H64: Automated exception reporting
B65: Revenue, expense, and payroll analytics auto-populate similarly, leveraging prior year data. | D65: CaseView automatically matches financial statements and flags errors if the balance sheet does not tie. | F65: Outstanding review notes are tracked | H65: Real-time dashboard updates
D66: MD&A statements is auto linked with financial statements
D67: Notes to financial statements auto-reconcile with financial data
A74: 6 | B74: Reporting
B76: Automated Report Generation | D76: Auto-updated Financials | F76: Automated Compliance checks | H76: Automation Tools:
H77: Caseview- Auto-report generation
B78: Financial Statements: Import client trial balance into CaseWare, auto-populate financial statement amounts in real time, and generate financial statements in CaseView. | D78: All numeric cells in CaseView are linked to the adjusted trial balance (ATB) and update automatically with any adjustments | F78: PPC checklist ms wor template are used to ensure disclosures and reporting requirements are met. | H78: Real-time financial updates
B79: Notes to Financial Statements: CaseView automatically updates notes to FS numbers, and auditors manually review and update significant accounting policies, contingent liabilities, and key disclosures. | D79: Prior-year amounts are automatically linked to the prior-year trial balance as beginning balances. | F79: CaseWare sign-off functionality ensures reviewer approvals before finalization | H79: Automated disclosure checks
B80: Audit Reports: Select and extract the appropriate PPC audit report template in CaseView, applying firm-wide formatting styles, footnotes, and headers for consistency. | D80: Year-related fields and client name cells automatically update according to the engagement settings. | F80: Lead sheets and trial balance mapping auto-reconcile to confirm reporting accuracy.
D81: All the calculations are formula-driven to ensure accuracy and eliminate manual errors.
D82: CaseView provides real-time updates, ensuring consistency across all financial statements.
A94: 7 | B94: Finalization
B96: E-signature process | D96: Automated Archiving | F96: Auto-generated Summary | H96: Automation Tools:
H97: DocuSign-Automated signing
B98: Engagement letters, Mgt letters and audit reports are sent for e-signature via DocuSign or Suralink, else outlook. | D98: CaseWare is roll-forwarded for the next audit cycle. | F98: Audit points are manually compiled into a PPT | H98: Automated File Management
D99: Sanitization removes unnecessary data from prior years. | F99: No automated process currently exists for generating summaries. | H99: Auto-generated closing memos
D100: Finalized CaseWare files are locked, restricting edits.
D101: Existing users retain view-only access for reference.
A108: 8 | B108: Monitoring
B110: Automated Follow-up | D110: Auto-scheduled Reviews | F110: Predictive Analytics | H110: Automation Tools:
H111: Automated recommendation tracking
B112: Outstanding PBC (Provided by Client) requests are flagged, prompting follow-up emails via Suralink button. | D112: No auto-scheduled reviews are currently in place. | F112: The lead sheet auto-generates based on prior-year trial balance (PY TB) and current data. | H112: Auto-scheduled follow-ups
D113: Review timelines are manually set and tracked by the team. | F113: CaseWare auto-calculates and compares current vs. prior-year financials, highlighting variances. | H113: AI-driven planning insights
D114: Sign-offs are manually monitored. | F114: These automated comparisons help identify unusual trends and potential risks.
F115: No AI-driven predictive analytics are currently in place.

Sheet Flow
B1: Prepare | Plan | Audit | Report | Close
B2: AiM: Flowchart | 7Mar26
B3: Phases | D3: Prepare | G3: Plan | M3: Audit | R3: Report | V3: Close
B4: Knowledge / context (documents and files) | D4: EL templates, HCLLP WP and PBC | E4: PPC, PBC and HCLLP WP | F4: PBC, HCLLP WP, PPC documents and templates | G4: PY TB, TB, HCLLP WP | H4: PY TB, TB, HCLLP WP | I4: PPC, PBC, HCLLP WP and Questionnaires | J4: PPC templates, risk criteria | L4: HCLLP WP, TW, Confirmations and signed documents | M4: PPC and Testwork files | N4: HCLLP WP, TP, PY TB and TB | O4: HCLLP WP, TW, FS, MD&A, Notes to financial statements | P4: Testwork file, Engagement team roles | Q4: PPC audit report templates | S4: PPC Checklist templates (Word) and lead sheet | T4: EL, management letters and audit reports | U4: CaseWare files | V4: Closing memos, summary and PPT | Y4: TB and PY TB
B5: Systems / databases and tools | C5: CaseWare and Monday.com | D5: CaseView, DocuSign and EL Generator | E5: PPC Checkpoint letter generator | F5: Doclink / Suralink, Outlook, CaseWare and PPC tool | G5: CaseWare | H5: CaseWare and TB auto-linking | J5: CaseWare | K5: CaseWare, Doclink / Suralink, Confirmation.com, auto-evidence tagging | L5: CaseWare, Doclink / Suralink, Confirmation.com and DocuSign | M5: CaseWare, Excel, Word, PDF and auto-referencing | N5: CaseWare, GenAI analytics and auto exception reporting | O5: CaseWare and Tie-out | P5: CaseWare | Q5: CaseWare, CaseView and GenAI reporter | R5: CaseWare and CaseView | S5: CaseWare, CaseView, Checklist and auto disclosure checker | T5: DocuSign, Doclink / Suralink and Outlook | U5: CaseWare | V5: Auto-generate summary, auto generate memos and PPT | X5: Auto scheduled follow-ups | Y5: CaseWare, auto recommendations tracker and GenAI insights
B6: AI jobs / agents (Agentic AI system through orchestration via MCP server protocol with multi-LLM complexion model) | C6: On-board client for new engagement: - Reference previous engagements in CaseWare - Validate client name, contact, industry and prior audit history - Populate Monday.com with the client and new engagement information - Update CaseWare accordingly | D6: Generate EL: - Get client and engagement details from CaseWare and Monday.com - Use predefined templates - Generate EL in CaseView | E6: Assess risks: - Select engagement details - Use client data to fill-in PPC Smart Practice Aids - Answer risk assessment questions - Categorize risks - Suggest audit procedure based on identified risks - Generate WPs and link to CaseWare | F6: Collect documents: - Follow CaseWare folder structure - Setup PBC list in Doclink/Suralink - Use audit prep guide - Request documents via secured document sharing system (Doclink or Suralink) - Request other documents via email (Outlook) - Doclink/Suralink highlights new uploads daily for easy tracking - Organize updated client and engagement documents in CaseWare folder structure - Extract required PPC templates and audit programs from PPC tool | G6: Analyze data: - Reference prior year trail balance (PY TB) already stored in CaseWare - Import current year trial balance (TB) from CaseWare documents - Generate preliminary analytical lead sheet - Populate lead sheet with prior-year figures, variance amounts and variance percentages - Analyze variances / flux analysis - Identify / flag unusual fluctuations | H6: Reconcile (auto-linking to TB): - Generate preliminary analytics in CaseWare from imported trial balance using last year's audited trail balance for comparison | I6: Assess risks: - Share questionnaire with the client to collect risk-related information - Use client provided details from questionnaire on financial processes, internal controls and compliance risks - Identify risks | J6: Test: - Generate sampling selections using PPC templates based on risk criteria - Validate trail balance data for completeness using auto-calculations in CaseWare - Flag duplicate transactions - Flag unusual patterns | K6: Collect and tag evidence: - Import pending items list into Doclink / Suralink - Import audit requests into Doclink / Suralink - Import selected transactions into Doclink / Suralink - Use PBC list updates to carry out testing - Initiate audit confirmations - Track in Confirmation.com streamlining bank, legal and third-party confirmations | L6: Collect documents: - Map Doclink / Suralink documents uploaded into CaseWare to relevant audit workpapers - Drop audit workpapers (WP) from PPC audit library into CaseWare - Copy Testwork (TW) from peer clients in CaseWare - Import confirmations from Confirmaations.com into CaseWare - Add signed documents from DocuSign to CaseWare | M6: Reference: - Assign file number in CaseWare - Use formulas in Excel to auto-reference file name as Testwork (TW) name - Reference PPC Word files - Reference PDF files - Generate references in lead sheet in CaseWare | N6: Generate analytics: - Generate analytics in CaseWare to compare imported trial balance (TB) with previous year's audited trial year (PY TB) - Generate analytics in CaseWare to compare with PY revenue, expense and payroll | O6: Generate insights: - Populate in CaseWare financial statements and management discussions and analysis (MD&A) sections using imported trial balance (TB) data - Flag errors in CaseView for mismatches between financial statements and balance sheet if they do not tie - Link MD&A statements with financial statements - Reconcile Notes to financial statements with financial data | P6: Track issues: - Insert comments on each Testwork (TW) file tagging team members for follow-ups | Q6: Generate report: - Financial Statements (FS): = Import client TB into CaseWare = Populate FS amounts = Generate FS in CaseView - Notes to financial statements (FS): = Update Notes to FS numbers in CaseView - Audit reports: = Select and extract appropriate PPC audit report template in CaseView = Apply firm-wide formatting style, footnotes and headers for consistency | R6: Update financials: - Link all numeric cells in CaseView to adjusted trial balance (ATB) - Update adjustments - Link prior-year amounts to prior-year trial balance (PY TB) as beginning balance - Update client name cells and year related fields in CaseView according to the engagement settings - Check all calculations are formula driven to ensure accuracy and avoid manual errors - Update financial statements real-time in CaseView for across the board consistency | S6: Compliance checks: - Use PPC checklist templates - Check disclosures - Update financial real-time - Auto-generate report in CaseView - Reconcile lead sheet and trail balance mapping to confirm reporting accuracy | T6: E-sign: - Send engagement letters (ELs), management letters and audit reports for e-signature via DocuSign or Doclink / Suralink or Outlook | U6: Archive: - Roll-forward CaseWare for next audit cycle - Remove unnecessary data from prior years (sanitize) - Lock finalized CaseWare files, restricting edits - Retain view-only access to existing users for reference | V6: Summarize: - Generate summary automatically - Compile audit points into PPT | W6: Follow-up: - Flag outstanding PBC (provided by client) requests - Prompt follow-up emails via Doclink / Suralink button | X6: Schedule reviews: - Set review timelines - Track review timelines - Monitor sign-offs | Y6: Predictive analytics: - Generate lead sheet based on prior-year trial balance (PY TB) and current data - Calculate in CaseWare current versus prior-year financials variances for comparison - Identify unseal trends and potential risks from comparisons
B7: Human intervention (Workspace with real-time dashboard updates) | C7: - Manually add new clients to CaseWare and Monday.com database - Partner approves acceptance of new or continuance, including independence before audit begins | D7: - Review EL for accuracy Send to client via DocuSign | E7: - Partner / Sr. Manager approves final materiality, significant risks and audit strategy | F7: - Client provides documents via secured document sharing system (uploads documents to Doclink / Suralink PBC list, assigned to specific line items | G7: - Review unusual fluctuations identified / flagged based on variance analysis | I7: - Client submits completed the questionnaire - Review completed questionnaire - Review identified risks | J7: - Review duplicate transactions identified - Review unusual patterns identified | K7: - Client provides documents via secured document sharing system (uploads documents to Doclink / Suralink PBC list, assigned to specific line items | O7: Handle exception reports using real-time dashboard updates | P7: - Track outstanding review notes | Q7: - Review and update significant accounting policies, contingent libraries and key disclosures | S7: - Ensure reporting requirements are met - Approve before finalization by using sign-off functionality in CaseWare | X7: - Conduct reviews as scheduled | Y7: - Review real-time dashboard updates and alerts
